README.txt
setup.py
collective/__init__.py
collective.javascript.jqueryui.egg-info/PKG-INFO
collective.javascript.jqueryui.egg-info/SOURCES.txt
collective.javascript.jqueryui.egg-info/dependency_links.txt
collective.javascript.jqueryui.egg-info/entry_points.txt
collective.javascript.jqueryui.egg-info/namespace_packages.txt
collective.javascript.jqueryui.egg-info/not-zip-safe
collective.javascript.jqueryui.egg-info/requires.txt
collective.javascript.jqueryui.egg-info/top_level.txt
collective/javascript/__init__.py
collective/javascript/jqueryui/__init__.py
collective/javascript/jqueryui/configure.zcml
collective/javascript/jqueryui/files/css/blitzer/jquery-ui.css
collective/javascript/jqueryui/files/css/blitzer/images/ui-bg_diagonals-thick_75_f3d8d8_40x40.png
collective/javascript/jqueryui/files/css/blitzer/images/ui-bg_dots-small_65_a6a6a6_2x2.png
collective/javascript/jqueryui/files/css/blitzer/images/ui-bg_flat_0_333333_40x100.png
collective/javascript/jqueryui/files/css/blitzer/images/ui-bg_flat_65_ffffff_40x100.png
collective/javascript/jqueryui/files/css/blitzer/images/ui-bg_flat_75_ffffff_40x100.png
collective/javascript/jqueryui/files/css/blitzer/images/ui-bg_glass_55_fbf8ee_1x400.png
collective/javascript/jqueryui/files/css/blitzer/images/ui-bg_highlight-hard_100_eeeeee_1x100.png
collective/javascript/jqueryui/files/css/blitzer/images/ui-bg_highlight-hard_100_f6f6f6_1x100.png
collective/javascript/jqueryui/files/css/blitzer/images/ui-bg_highlight-soft_15_cc0000_1x100.png
collective/javascript/jqueryui/files/css/blitzer/images/ui-icons_004276_256x240.png
collective/javascript/jqueryui/files/css/blitzer/images/ui-icons_cc0000_256x240.png
collective/javascript/jqueryui/files/css/blitzer/images/ui-icons_ffffff_256x240.png
collective/javascript/jqueryui/files/css/eggplant/jquery-ui.css
collective/javascript/jqueryui/files/css/eggplant/images/ui-bg_flat_0_aaaaaa_40x100.png
collective/javascript/jqueryui/files/css/eggplant/images/ui-bg_flat_0_eeeeee_40x100.png
collective/javascript/jqueryui/files/css/eggplant/images/ui-bg_flat_55_994d53_40x100.png
collective/javascript/jqueryui/files/css/eggplant/images/ui-bg_flat_55_fafafa_40x100.png
collective/javascript/jqueryui/files/css/eggplant/images/ui-bg_gloss-wave_30_3d3644_500x100.png
collective/javascript/jqueryui/files/css/eggplant/images/ui-bg_highlight-soft_100_dcd9de_1x100.png
