Metadata-Version: 1.0
Name: collective.javascript.jqueryui
Version: 1.8.4
Summary: Javascript files for jquery ui
Home-page: http://svn.plone.org/svn/collective/
Author: Nathan Van Gheem
Author-email: vangheem@gmail.com
License: GPL
Keywords: plone jquery jqueryui ui
Platform: UNKNOWN
Classifier: Programming Language :: Python
